contextual/__init__.py
contextual/graph/__init__.py
contextual/graph/py.typed
contextual/graph/components/__init__.py
contextual/graph/components/base.py
contextual/graph/components/embedding/__init__.py
contextual/graph/components/embedding/base.py
contextual/graph/components/embedding/openai_embedding.py
contextual/graph/components/extractor_schema/__init__.py
contextual/graph/components/extractor_schema/base_schema.py
contextual/graph/components/extractor_schema/mongo_schema_extractor.py
contextual/graph/components/nodes/__init__.py
contextual/graph/components/nodes/base.py
contextual/graph/components/nodes/extractor_node.py
contextual/graph/components/nodes/vector_inserter_node.py
contextual/graph/components/nodes/vision_locator_node.py
contextual/graph/components/nodes/zerox_ocr_node.py
contextual/graph/components/observability/__init__.py
contextual/graph/components/observability/mongo_tracer.py
contextual/graph/components/observability/tracer_interface.py
contextual/graph/components/observability/tracing_middleware.py
contextual/graph/components/ocr/__init__.py
contextual/graph/components/ocr/base.py
contextual/graph/components/ocr/zerox_ocr.py
contextual/graph/components/repositories/__init__.py
contextual/graph/components/repositories/crud_base.py
contextual/graph/components/repositories/execution_repository.py
contextual/graph/components/repositories/mongodb_crud_repository.py
contextual/graph/components/repositories/supabase_crud_repository.py
contextual/graph/components/vector_stores/__init__.py
contextual/graph/components/vector_stores/base.py
contextual/graph/components/vector_stores/supabase_vector_store.py
contextual/graph/exceptions/__init__.py
contextual/graph/exceptions/components/__init__.py
contextual/graph/exceptions/components/ocr/__init__.py
contextual/graph/exceptions/components/ocr/ocr_exceptions.py
contextual/graph/exceptions/components/repositories/__init__.py
contextual/graph/exceptions/components/repositories/mongodb_exceptions.py
contextual_studio_ai_graph-0.1.12.dist-info/licenses/LICENSE
contextual_studio_ai_graph-0.1.12.dist-info/METADATA
contextual_studio_ai_graph-0.1.12.dist-info/WHEEL
contextual_studio_ai_graph-0.1.12.dist-info/top_level.txt
contextual_studio_ai_graph-0.1.12.dist-info/RECORD
