Metadata-Version: 2.4
Name: contextual-studio-ai-graph
Version: 0.1.12
Summary: IA library to create logic graphs and components.
Author-email: Jorge Resino <jorgeresino143@gmail.com>
Maintainer-email: Jorge Resino <jorgeresino143@gmail.com>
License: MIT
Project-URL: Homepage, https://contextualstudio.com/
Project-URL: Documentation, https://github.com/contextual-studio/graph
Project-URL: Repository, https://github.com/contextual-studio/graph
Classifier: Development Status :: 4 - Beta
Classifier: Intended Audience :: Developers
Classifier: Topic :: Software Development :: Build Tools
Classifier: Programming Language :: Python :: 3.12
Requires-Python: >=3.12
License-File: LICENSE
Requires-Dist: aiohappyeyeballs==2.6.1
Requires-Dist: aiohttp==3.12.15
Requires-Dist: aiosignal==1.4.0
Requires-Dist: annotated-types==0.7.0
Requires-Dist: anyio==4.11.0
Requires-Dist: attrs==25.3.0
Requires-Dist: cachetools==6.2.0
Requires-Dist: certifi==2025.8.3
Requires-Dist: cffi==2.0.0
Requires-Dist: charset-normalizer==3.4.3
Requires-Dist: colorama==0.4.6
Requires-Dist: cryptography==46.0.2
Requires-Dist: dataclasses-json==0.6.7
Requires-Dist: deprecation==2.1.0
Requires-Dist: distro==1.9.0
Requires-Dist: filetype==1.2.0
Requires-Dist: frozenlist==1.7.0
Requires-Dist: google-ai-generativelanguage==0.7.0
Requires-Dist: google-api-core==2.25.2
Requires-Dist: google-auth==2.41.1
Requires-Dist: googleapis-common-protos==1.70.0
Requires-Dist: greenlet==3.2.4
Requires-Dist: grpcio==1.75.1
Requires-Dist: grpcio-status==1.75.1
Requires-Dist: h11==0.16.0
Requires-Dist: h2==4.3.0
Requires-Dist: hpack==4.1.0
Requires-Dist: httpcore==1.0.9
Requires-Dist: httpx==0.28.1
Requires-Dist: httpx-sse==0.4.1
Requires-Dist: hyperframe==6.1.0
Requires-Dist: idna==3.10
Requires-Dist: jiter==0.11.0
Requires-Dist: jsonpatch==1.33
Requires-Dist: jsonpointer==3.0.0
Requires-Dist: langchain==0.3.27
Requires-Dist: langchain-community==0.3.30
Requires-Dist: langchain-core==0.3.78
Requires-Dist: langchain-google-genai==2.1.12
Requires-Dist: langchain-openai==0.3.34
Requires-Dist: langchain-text-splitters==0.3.11
Requires-Dist: langgraph==0.6.8
Requires-Dist: langgraph-checkpoint==2.1.1
Requires-Dist: langgraph-prebuilt==0.6.4
Requires-Dist: langgraph-sdk==0.2.9
Requires-Dist: langsmith==0.4.32
Requires-Dist: marshmallow==3.26.1
Requires-Dist: multidict==6.6.4
Requires-Dist: mypy-extensions==1.1.0
Requires-Dist: numpy==2.3.3
Requires-Dist: openai==2.1.0
Requires-Dist: orjson==3.11.3
Requires-Dist: ormsgpack==1.10.0
Requires-Dist: packaging==25.0
Requires-Dist: postgrest==2.24.0
Requires-Dist: propcache==0.3.2
Requires-Dist: proto-plus==1.26.1
Requires-Dist: protobuf==6.32.1
Requires-Dist: pyasn1==0.6.1
Requires-Dist: pyasn1-modules==0.4.2
Requires-Dist: pycparser==2.23
Requires-Dist: pydantic==2.11.10
Requires-Dist: pydantic-core==2.33.2
Requires-Dist: pydantic-settings==2.11.0
Requires-Dist: pyjwt==2.10.1
Requires-Dist: python-multipart>=0.0.20
Requires-Dist: pymupdf>=1.25.1
Requires-Dist: python-dotenv==1.1.1
Requires-Dist: pyyaml==6.0.3
Requires-Dist: regex==2025.9.18
Requires-Dist: requests==2.32.5
Requires-Dist: requests-toolbelt==1.0.0
Requires-Dist: rsa==4.9.1
Requires-Dist: sniffio==1.3.1
Requires-Dist: sqlalchemy==2.0.43
Requires-Dist: strenum==0.4.15
Requires-Dist: supabase<3.0.0,>=2.24.0
Requires-Dist: supabase-auth<3.0.0,>=2.24.0
Requires-Dist: supabase-functions<3.0.0,>=2.24.0
Requires-Dist: storage3<3.0.0,>=2.24.0
Requires-Dist: realtime<3.0.0,>=2.24.0
Requires-Dist: tenacity==9.1.2
Requires-Dist: tiktoken==0.11.0
Requires-Dist: tqdm==4.67.1
Requires-Dist: typing-extensions==4.15.0
Requires-Dist: typing-inspect==0.9.0
Requires-Dist: typing-inspection==0.4.2
Requires-Dist: urllib3==2.5.0
Requires-Dist: websockets==15.0.1
Requires-Dist: xxhash==3.6.0
Requires-Dist: yarl==1.20.1
Requires-Dist: zstandard==0.25.0
Requires-Dist: pre-commit==4.3.0
Requires-Dist: contextual-studio-ai-zerox==0.1.1
Requires-Dist: pymupdf>=1.25.3
Requires-Dist: loguru==0.7.3
Requires-Dist: pymongo==4.15.4
Provides-Extra: dev-local
Dynamic: license-file
